MANIFEST.in
setup.py
dexy_templates/__init__.py
dexy_templates/__init__.pyc
dexy_templates.egg-info/PKG-INFO
dexy_templates.egg-info/SOURCES.txt
dexy_templates.egg-info/dependency_links.txt
dexy_templates.egg-info/requires.txt
dexy_templates.egg-info/top_level.txt
dexy_templates/code-journal-html-python-template/_template.html
dexy_templates/code-journal-html-python-template/code001.py
dexy_templates/code-journal-html-python-template/dexy.conf
dexy_templates/code-journal-html-python-template/dexy.yaml
dexy_templates/code-journal-html-python-template/journal.html
dexy_templates/code-journal-html-python-template/pygments.css
dexy_templates/code-journal-html-python-template/zp-compressed.css
dexy_templates/code-journal-html-python-template/zp-print.css
dexy_templates/code-journal-html-r-template/_template.html
dexy_templates/code-journal-html-r-template/code001.R
dexy_templates/code-journal-html-r-template/dexy.conf
dexy_templates/code-journal-html-r-template/dexy.yaml
dexy_templates/code-journal-html-r-template/journal.html
dexy_templates/code-journal-html-r-template/zp-compressed.css
dexy_templates/code-journal-html-r-template/zp-print.css
dexy_templates/code-journal-markdown-matplotlib-template/_template.html
dexy_templates/code-journal-markdown-matplotlib-template/code001.py
dexy_templates/code-journal-markdown-matplotlib-template/code002.py
dexy_templates/code-journal-markdown-matplotlib-template/data.csv
dexy_templates/code-journal-markdown-matplotlib-template/dexy.conf
dexy_templates/code-journal-markdown-matplotlib-template/dexy.yaml
dexy_templates/code-journal-markdown-matplotlib-template/index.md
dexy_templates/code-journal-markdown-matplotlib-template/zp-compressed.css
dexy_templates/code-journal-markdown-matplotlib-template/zp-print.css
dexy_templates/code-journal-markdown-r-template/_template.html
dexy_templates/code-journal-markdown-r-template/code001.R
dexy_templates/code-journal-markdown-r-template/dexy.conf
dexy_templates/code-journal-markdown-r-template/dexy.yaml
dexy_templates/code-journal-markdown-r-template/index.md
dexy_templates/code-journal-markdown-r-template/zp-compressed.css
